[
    {
      "id": "1",
      "name": "learn JavaScript",
      "description": "doing first task",
      "date": "2023-12-25",
      "level": "low"
    },
    {
      "id": "2",
      "name": "learn HTML",
      "description": "doing second task",
      "date": "2023-12-26",
      "level": "medium"
    },
    {
      "id": "3",
      "name": "learn CSS",
      "description": "doing third task",
      "date": "2023-12-27",
      "level": "high"
    },
    {
      "id": "4",
      "name": "learn REACT.JS",
      "description": "doing fourth task",
      "date": "2023-12-28",
      "level": "low"
    },
    {
      "id": "5",
      "name": "learn NODE.JS",
      "description": "doing fifth task",
      "date": "2023-12-29",
      "level": "medium"
    }
  ]
  